instagram_monitor.py
instagram_monitor-2.0.4.dist-info/licenses/LICENSE
instagram_monitor-2.0.4.dist-info/METADATA
instagram_monitor-2.0.4.dist-info/WHEEL
instagram_monitor-2.0.4.dist-info/entry_points.txt
instagram_monitor-2.0.4.dist-info/top_level.txt
instagram_monitor-2.0.4.dist-info/RECORD
