Metadata-Version: 2.4
Name: instagram_monitor
Version: 2.0.4
Summary: Tool implementing real-time tracking of Instagram users activities and profile changes
Author-email: Michal Szymanski <misiektoja-pypi@rm-rf.ninja>
License-Expression: GPL-3.0-or-later
Project-URL: Homepage, https://github.com/misiektoja/instagram_monitor
Project-URL: Source, https://github.com/misiektoja/instagram_monitor
Project-URL: Changelog, https://github.com/misiektoja/instagram_monitor/blob/main/RELEASE_NOTES.md
Keywords: instagram,monitoring,tracking,real-time,osint,instaloader
Classifier: Programming Language :: Python :: 3
Classifier: Operating System :: OS Independent
Classifier: Operating System :: Microsoft :: Windows
Classifier: Operating System :: POSIX :: Linux
Classifier: Operating System :: MacOS :: MacOS X
Requires-Python: >=3.9
License-File: LICENSE
Requires-Dist: instaloader>=4.12
Requires-Dist: requests>=2.0
Requires-Dist: python-dateutil>=2.8
Requires-Dist: pytz>=2020.1
Requires-Dist: tzlocal>=4.0
Requires-Dist: python-dotenv>=0.19
Requires-Dist: tqdm>=4.0
Dynamic: license-file
